{"remainingRequest":"C:\\Users\\hp\\Documents\\soptorshi-jhipster\\node_modules\\thread-loader\\dist\\cjs.js??ref--9-2!C:\\Users\\hp\\Documents\\soptorshi-jhipster\\node_modules\\ts-loader\\index.js??ref--9-3!C:\\Users\\hp\\Documents\\soptorshi-jhipster\\node_modules\\angular-router-loader\\src\\index.js!C:\\Users\\hp\\Documents\\soptorshi-jhipster\\node_modules\\tslint-loader\\index.js!C:\\Users\\hp\\Documents\\soptorshi-jhipster\\src\\main\\webapp\\app\\home-extended\\home-extended.component.ts","dependencies":[{"path":"C:\\Users\\hp\\Documents\\soptorshi-jhipster\\src\\main\\webapp\\app\\home-extended\\home-extended.component.ts","mtime":1625565388302},{"path":"C:\\Users\\hp\\Documents\\soptorshi-jhipster\\node_modules\\angular2-template-loader\\index.js","mtime":1486570058000},{"path":"C:\\Users\\hp\\Documents\\soptorshi-jhipster\\node_modules\\cache-loader\\dist\\cjs.js","mtime":499162500000},{"path":"C:\\Users\\hp\\Documents\\soptorshi-jhipster\\node_modules\\thread-loader\\dist\\cjs.js","mtime":499162500000},{"path":"C:\\Users\\hp\\Documents\\soptorshi-jhipster\\node_modules\\ts-loader\\index.js","mtime":1545640398000},{"path":"C:\\Users\\hp\\Documents\\soptorshi-jhipster\\node_modules\\angular-router-loader\\src\\index.js","mtime":1512749902000},{"path":"C:\\Users\\hp\\Documents\\soptorshi-jhipster\\node_modules\\tslint-loader\\index.js","mtime":1519899048000}],"contextDependencies":[],"result":["\"use strict\";\r\nObject.defineProperty(exports, \"__esModule\", { value: true });\r\nvar tslib_1 = require(\"tslib\");\r\nvar core_1 = require(\"@angular/core\");\r\nvar ng_jhipster_1 = require(\"ng-jhipster\");\r\nvar core_2 = require(\"app/core\");\r\nvar employee_1 = require(\"app/entities/employee\");\r\nvar department_1 = require(\"app/entities/department\");\r\nvar designation_1 = require(\"app/entities/designation\");\r\nvar home_1 = require(\"app/home\");\r\nvar router_1 = require(\"@angular/router\");\r\nvar HomeExtendedComponent = /** @class */ (function (_super) {\r\n    tslib_1.__extends(HomeExtendedComponent, _super);\r\n    function HomeExtendedComponent(accountService, loginModalService, eventManager, employeeService, jhiAlertService, departmentService, designationService, router) {\r\n        var _this = _super.call(this, accountService, loginModalService, eventManager, employeeService, jhiAlertService, departmentService, designationService) || this;\r\n        _this.accountService = accountService;\r\n        _this.loginModalService = loginModalService;\r\n        _this.eventManager = eventManager;\r\n        _this.employeeService = employeeService;\r\n        _this.jhiAlertService = jhiAlertService;\r\n        _this.departmentService = departmentService;\r\n        _this.designationService = designationService;\r\n        _this.router = router;\r\n        return _this;\r\n    }\r\n    HomeExtendedComponent.prototype.fetchLoggedEmployeeInformation = function () {\r\n        var _this = this;\r\n        this.employeeService\r\n            .query({\r\n            'employeeId.equals': this.account.login,\r\n            page: 0,\r\n            size: 1\r\n        })\r\n            .subscribe(function (res) {\r\n            _this.employee = res.body[0];\r\n            _this.fetchAdditionalInformation();\r\n        }, function (res) { return _this.jhiAlertService.error('Error in fetching logged employee information'); });\r\n    };\r\n    HomeExtendedComponent.prototype.fetchAdditionalInformation = function () {\r\n        var _this = this;\r\n        this.departmentService.find(this.employee.departmentId).subscribe(function (res) { return (_this.department = res.body); });\r\n        this.designationService\r\n            .find(this.employee.designationId)\r\n            .subscribe(function (res) { return (_this.designation = res.body); });\r\n    };\r\n    HomeExtendedComponent.prototype.ngOnInit = function () {\r\n        var _this = this;\r\n        if (!this.isAuthenticated())\r\n            this.router.navigate(['/login']);\r\n        this.accountService.identity().then(function (account) {\r\n            _this.account = account;\r\n            _this.fetchLoggedEmployeeInformation();\r\n        });\r\n        this.registerAuthenticationSuccess();\r\n    };\r\n    HomeExtendedComponent.prototype.registerAuthenticationSuccess = function () {\r\n        var _this = this;\r\n        this.eventManager.subscribe('authenticationSuccess', function (message) {\r\n            _this.accountService.identity().then(function (account) {\r\n                _this.account = account;\r\n            });\r\n        });\r\n    };\r\n    HomeExtendedComponent.prototype.isAuthenticated = function () {\r\n        return this.accountService.isAuthenticated();\r\n    };\r\n    HomeExtendedComponent.prototype.login = function () {\r\n        this.router.navigate(['/login']);\r\n    };\r\n    var _a, _b, _c, _d, _e, _f, _g, _h;\r\n    HomeExtendedComponent = tslib_1.__decorate([\r\n        core_1.Component({\r\n            selector: 'jhi-home-extended',\r\n            templateUrl: './home-extended.component.html',\r\n            styleUrls: ['home-extended.css']\r\n        }),\r\n        tslib_1.__metadata(\"design:paramtypes\", [typeof (_a = typeof core_2.AccountService !== \"undefined\" && core_2.AccountService) === \"function\" ? _a : Object, typeof (_b = typeof core_2.LoginModalService !== \"undefined\" && core_2.LoginModalService) === \"function\" ? _b : Object, typeof (_c = typeof ng_jhipster_1.JhiEventManager !== \"undefined\" && ng_jhipster_1.JhiEventManager) === \"function\" ? _c : Object, typeof (_d = typeof employee_1.EmployeeService !== \"undefined\" && employee_1.EmployeeService) === \"function\" ? _d : Object, typeof (_e = typeof ng_jhipster_1.JhiAlertService !== \"undefined\" && ng_jhipster_1.JhiAlertService) === \"function\" ? _e : Object, typeof (_f = typeof department_1.DepartmentService !== \"undefined\" && department_1.DepartmentService) === \"function\" ? _f : Object, typeof (_g = typeof designation_1.DesignationService !== \"undefined\" && designation_1.DesignationService) === \"function\" ? _g : Object, typeof (_h = typeof router_1.Router !== \"undefined\" && router_1.Router) === \"function\" ? _h : Object])\r\n    ], HomeExtendedComponent);\r\n    return HomeExtendedComponent;\r\n}(home_1.HomeComponent));\r\nexports.HomeExtendedComponent = HomeExtendedComponent;\r\n",{"version":3,"file":"C:\\Users\\hp\\Documents\\soptorshi-jhipster\\src\\main\\webapp\\app\\home-extended\\home-extended.component.ts","sourceRoot":"","sources":["C:\\Users\\hp\\Documents\\soptorshi-jhipster\\node_modules\\angular-router-loader\\src\\index.js!C:\\Users\\hp\\Documents\\soptorshi-jhipster\\node_modules\\tslint-loader\\index.js!C:\\Users\\hp\\Documents\\soptorshi-jhipster\\src\\main\\webapp\\app\\home-extended\\home-extended.component.ts"],"names":[],"mappings":";;;AAAA,sCAAiE;AAEjE,2CAA+D;AAE/D,iCAAsE;AAEtE,kDAAwD;AAIxD,sDAA4D;AAC5D,wDAA8D;AAE9D,iCAAyC;AACzC,0CAAyC;AAOzC;IAA2C,iDAAa;IAOpD,+BACW,cAA8B,EAC9B,iBAAoC,EACpC,YAA6B,EAC7B,eAAgC,EAChC,eAAgC,EAChC,iBAAoC,EACpC,kBAAsC,EACtC,MAAc;QARzB,YAUI,kBAAM,cAAc,EAAE,iBAAiB,EAAE,YAAY,EAAE,eAAe,EAAE,eAAe,EAAE,iBAAiB,EAAE,kBAAkB,CAAC,SAClI;QAVU,oBAAc,GAAd,cAAc,CAAgB;QAC9B,uBAAiB,GAAjB,iBAAiB,CAAmB;QACpC,kBAAY,GAAZ,YAAY,CAAiB;QAC7B,qBAAe,GAAf,eAAe,CAAiB;QAChC,qBAAe,GAAf,eAAe,CAAiB;QAChC,uBAAiB,GAAjB,iBAAiB,CAAmB;QACpC,wBAAkB,GAAlB,kBAAkB,CAAoB;QACtC,YAAM,GAAN,MAAM,CAAQ;;IAGzB,CAAC;IAED,8DAA8B,GAA9B;QAAA,iBAcC;QAbG,IAAI,CAAC,eAAe;aACf,KAAK,CAAC;YACH,mBAAmB,EAAE,IAAI,CAAC,OAAO,CAAC,KAAK;YACvC,IAAI,EAAE,CAAC;YACP,IAAI,EAAE,CAAC;SACV,CAAC;aACD,SAAS,CACN,UAAC,GAA8B;YAC3B,KAAI,CAAC,QAAQ,GAAG,GAAG,CAAC,IAAI,CAAC,CAAC,CAAC,CAAC;YAC5B,KAAI,CAAC,0BAA0B,EAAE,CAAC;QACtC,CAAC,EACD,UAAC,GAAsB,IAAK,OAAA,KAAI,CAAC,eAAe,CAAC,KAAK,CAAC,+CAA+C,CAAC,EAA3E,CAA2E,CAC1G,CAAC;IACV,CAAC;IAED,0DAA0B,GAA1B;QAAA,iBAKC;QAJG,IAAI,CAAC,iBAAiB,CAAC,IAAI,CAAC,IAAI,CAAC,QAAQ,CAAC,YAAY,CAAC,CAAC,SAAS,CAAC,UAAC,GAA8B,IAAK,OAAA,CAAC,KAAI,CAAC,UAAU,GAAG,GAAG,CAAC,IAAI,CAAC,EAA5B,CAA4B,CAAC,CAAC;QACpI,IAAI,CAAC,kBAAkB;aAClB,IAAI,CAAC,IAAI,CAAC,QAAQ,CAAC,aAAa,CAAC;aACjC,SAAS,CAAC,UAAC,GAA+B,IAAK,OAAA,CAAC,KAAI,CAAC,WAAW,GAAG,GAAG,CAAC,IAAI,CAAC,EAA7B,CAA6B,CAAC,CAAC;IACvF,CAAC;IAED,wCAAQ,GAAR;QAAA,iBAOC;QANG,IAAI,CAAC,IAAI,CAAC,eAAe,EAAE;YAAE,IAAI,CAAC,MAAM,CAAC,QAAQ,CAAC,CAAC,QAAQ,CAAC,CAAC,CAAC;QAC9D,IAAI,CAAC,cAAc,CAAC,QAAQ,EAAE,CAAC,IAAI,CAAC,UAAC,OAAgB;YACjD,KAAI,CAAC,OAAO,GAAG,OAAO,CAAC;YACvB,KAAI,CAAC,8BAA8B,EAAE,CAAC;QAC1C,CAAC,CAAC,CAAC;QACH,IAAI,CAAC,6BAA6B,EAAE,CAAC;IACzC,CAAC;IAED,6DAA6B,GAA7B;QAAA,iBAMC;QALG,IAAI,CAAC,YAAY,CAAC,SAAS,CAAC,uBAAuB,EAAE,UAAA,OAAO;YACxD,KAAI,CAAC,cAAc,CAAC,QAAQ,EAAE,CAAC,IAAI,CAAC,UAAA,OAAO;gBACvC,KAAI,CAAC,OAAO,GAAG,OAAO,CAAC;YAC3B,CAAC,CAAC,CAAC;QACP,CAAC,CAAC,CAAC;IACP,CAAC;IAED,+CAAe,GAAf;QACI,OAAO,IAAI,CAAC,cAAc,CAAC,eAAe,EAAE,CAAC;IACjD,CAAC;IAED,qCAAK,GAAL;QACI,IAAI,CAAC,MAAM,CAAC,QAAQ,CAAC,CAAC,QAAQ,CAAC,CAAC,CAAC;IACrC,CAAC;;IAlEQ,qBAAqB;QALjC,gBAAS,CAAC;YACP,QAAQ,EAAE,mBAAmB;YAC7B,WAAW,EAAE,gCAAgC;YAC7C,SAAS,EAAE,CAAC,mBAAmB,CAAC;SACnC,CAAC;qEAS6B,qBAAc,oBAAd,qBAAc,oDACX,wBAAiB,oBAAjB,wBAAiB,oDACtB,6BAAe,oBAAf,6BAAe,oDACZ,0BAAe,oBAAf,0BAAe,oDACf,6BAAe,oBAAf,6BAAe,oDACb,8BAAiB,oBAAjB,8BAAiB,oDAChB,gCAAkB,oBAAlB,gCAAkB,oDAC9B,eAAM,oBAAN,eAAM;OAfhB,qBAAqB,CAmEjC;IAAD,4BAAC;CAAA,AAnED,CAA2C,oBAAa,GAmEvD;AAnEY,sDAAqB","sourcesContent":["import { AfterViewInit, Component, OnInit } from '@angular/core';\r\nimport { NgbModalRef } from '@ng-bootstrap/ng-bootstrap';\r\nimport { JhiAlertService, JhiEventManager } from 'ng-jhipster';\r\n\r\nimport { LoginModalService, AccountService, Account } from 'app/core';\r\nimport { Employee, IEmployee } from 'app/shared/model/employee.model';\r\nimport { EmployeeService } from 'app/entities/employee';\r\nimport { HttpErrorResponse, HttpResponse } from '@angular/common/http';\r\nimport { Department, IDepartment } from 'app/shared/model/department.model';\r\nimport { Designation, IDesignation } from 'app/shared/model/designation.model';\r\nimport { DepartmentService } from 'app/entities/department';\r\nimport { DesignationService } from 'app/entities/designation';\r\nimport { filter, map } from 'rxjs/operators';\r\nimport { HomeComponent } from 'app/home';\r\nimport { Router } from '@angular/router';\r\n\r\n@Component({\r\n    selector: 'jhi-home-extended',\r\n    templateUrl: './home-extended.component.html',\r\n    styleUrls: ['home-extended.css']\r\n})\r\nexport class HomeExtendedComponent extends HomeComponent implements OnInit {\r\n    account: Account;\r\n    modalRef: NgbModalRef;\r\n    employee: Employee;\r\n    department: Department;\r\n    designation: Designation;\r\n\r\n    constructor(\r\n        public accountService: AccountService,\r\n        public loginModalService: LoginModalService,\r\n        public eventManager: JhiEventManager,\r\n        public employeeService: EmployeeService,\r\n        public jhiAlertService: JhiAlertService,\r\n        public departmentService: DepartmentService,\r\n        public designationService: DesignationService,\r\n        public router: Router\r\n    ) {\r\n        super(accountService, loginModalService, eventManager, employeeService, jhiAlertService, departmentService, designationService);\r\n    }\r\n\r\n    fetchLoggedEmployeeInformation() {\r\n        this.employeeService\r\n            .query({\r\n                'employeeId.equals': this.account.login,\r\n                page: 0,\r\n                size: 1\r\n            })\r\n            .subscribe(\r\n                (res: HttpResponse<IEmployee[]>) => {\r\n                    this.employee = res.body[0];\r\n                    this.fetchAdditionalInformation();\r\n                },\r\n                (res: HttpErrorResponse) => this.jhiAlertService.error('Error in fetching logged employee information')\r\n            );\r\n    }\r\n\r\n    fetchAdditionalInformation() {\r\n        this.departmentService.find(this.employee.departmentId).subscribe((res: HttpResponse<IDepartment>) => (this.department = res.body));\r\n        this.designationService\r\n            .find(this.employee.designationId)\r\n            .subscribe((res: HttpResponse<IDesignation>) => (this.designation = res.body));\r\n    }\r\n\r\n    ngOnInit() {\r\n        if (!this.isAuthenticated()) this.router.navigate(['/login']);\r\n        this.accountService.identity().then((account: Account) => {\r\n            this.account = account;\r\n            this.fetchLoggedEmployeeInformation();\r\n        });\r\n        this.registerAuthenticationSuccess();\r\n    }\r\n\r\n    registerAuthenticationSuccess() {\r\n        this.eventManager.subscribe('authenticationSuccess', message => {\r\n            this.accountService.identity().then(account => {\r\n                this.account = account;\r\n            });\r\n        });\r\n    }\r\n\r\n    isAuthenticated() {\r\n        return this.accountService.isAuthenticated();\r\n    }\r\n\r\n    login() {\r\n        this.router.navigate(['/login']);\r\n    }\r\n}\r\n"]}]}