{"remainingRequest":"C:\\Users\\hp\\Documents\\soptorshi-jhipster\\node_modules\\thread-loader\\dist\\cjs.js??ref--9-2!C:\\Users\\hp\\Documents\\soptorshi-jhipster\\node_modules\\ts-loader\\index.js??ref--9-3!C:\\Users\\hp\\Documents\\soptorshi-jhipster\\node_modules\\angular-router-loader\\src\\index.js!C:\\Users\\hp\\Documents\\soptorshi-jhipster\\node_modules\\tslint-loader\\index.js!C:\\Users\\hp\\Documents\\soptorshi-jhipster\\src\\main\\webapp\\app\\entities\\salary-extended\\salary-extended.component.ts","dependencies":[{"path":"C:\\Users\\hp\\Documents\\soptorshi-jhipster\\src\\main\\webapp\\app\\entities\\salary-extended\\salary-extended.component.ts","mtime":1625565387745},{"path":"C:\\Users\\hp\\Documents\\soptorshi-jhipster\\node_modules\\angular2-template-loader\\index.js","mtime":1486570058000},{"path":"C:\\Users\\hp\\Documents\\soptorshi-jhipster\\node_modules\\cache-loader\\dist\\cjs.js","mtime":499162500000},{"path":"C:\\Users\\hp\\Documents\\soptorshi-jhipster\\node_modules\\thread-loader\\dist\\cjs.js","mtime":499162500000},{"path":"C:\\Users\\hp\\Documents\\soptorshi-jhipster\\node_modules\\ts-loader\\index.js","mtime":1545640398000},{"path":"C:\\Users\\hp\\Documents\\soptorshi-jhipster\\node_modules\\angular-router-loader\\src\\index.js","mtime":1512749902000},{"path":"C:\\Users\\hp\\Documents\\soptorshi-jhipster\\node_modules\\tslint-loader\\index.js","mtime":1519899048000}],"contextDependencies":[],"result":["\"use strict\";\r\nObject.defineProperty(exports, \"__esModule\", { value: true });\r\nvar tslib_1 = require(\"tslib\");\r\nvar core_1 = require(\"@angular/core\");\r\nvar router_1 = require(\"@angular/router\");\r\nvar ng_jhipster_1 = require(\"ng-jhipster\");\r\nvar core_2 = require(\"app/core\");\r\nvar salary_extended_service_1 = require(\"./salary-extended.service\");\r\nvar salary_1 = require(\"app/entities/salary\");\r\nvar SalaryExtendedComponent = /** @class */ (function (_super) {\r\n    tslib_1.__extends(SalaryExtendedComponent, _super);\r\n    function SalaryExtendedComponent(salaryService, parseLinks, jhiAlertService, accountService, activatedRoute, router, eventManager) {\r\n        var _this = _super.call(this, salaryService, parseLinks, jhiAlertService, accountService, activatedRoute, router, eventManager) || this;\r\n        _this.salaryService = salaryService;\r\n        _this.parseLinks = parseLinks;\r\n        _this.jhiAlertService = jhiAlertService;\r\n        _this.accountService = accountService;\r\n        _this.activatedRoute = activatedRoute;\r\n        _this.router = router;\r\n        _this.eventManager = eventManager;\r\n        return _this;\r\n    }\r\n    SalaryExtendedComponent.prototype.loadAll = function () {\r\n        var _this = this;\r\n        if (this.currentSearch) {\r\n            this.currentSearch = this.currentSearch + ' ' + this.salary.employeeId;\r\n            this.salaryService\r\n                .search({\r\n                page: this.page - 1,\r\n                query: this.currentSearch,\r\n                size: this.itemsPerPage,\r\n                sort: this.sort()\r\n            })\r\n                .subscribe(function (res) { return _this.paginateSalaries(res.body, res.headers); }, function (res) { return _this.onError(res.message); });\r\n            return;\r\n        }\r\n        this.salaryService\r\n            .query({\r\n            'employeeId.equals': this.salary.employeeId,\r\n            page: this.page - 1,\r\n            size: this.itemsPerPage,\r\n            sort: this.sort()\r\n        })\r\n            .subscribe(function (res) { return _this.paginateSalaries(res.body, res.headers); }, function (res) { return _this.onError(res.message); });\r\n    };\r\n    SalaryExtendedComponent.prototype.loadPage = function (page) {\r\n        if (page !== this.previousPage) {\r\n            this.previousPage = page;\r\n            this.transition();\r\n        }\r\n    };\r\n    SalaryExtendedComponent.prototype.transition = function () {\r\n        this.router.navigate(['/salary'], {\r\n            queryParams: {\r\n                page: this.page,\r\n                size: this.itemsPerPage,\r\n                search: this.currentSearch,\r\n                sort: this.predicate + ',' + (this.reverse ? 'asc' : 'desc')\r\n            }\r\n        });\r\n        this.loadAll();\r\n    };\r\n    SalaryExtendedComponent.prototype.clear = function () {\r\n        this.page = 0;\r\n        this.currentSearch = '';\r\n        this.router.navigate([\r\n            '/salary',\r\n            {\r\n                page: this.page,\r\n                sort: this.predicate + ',' + (this.reverse ? 'asc' : 'desc')\r\n            }\r\n        ]);\r\n        this.loadAll();\r\n    };\r\n    SalaryExtendedComponent.prototype.back = function () {\r\n        window.history.back();\r\n    };\r\n    SalaryExtendedComponent.prototype.search = function (query) {\r\n        if (!query) {\r\n            return this.clear();\r\n        }\r\n        this.page = 0;\r\n        this.currentSearch = query;\r\n        this.router.navigate([\r\n            '/salary',\r\n            {\r\n                search: this.currentSearch,\r\n                page: this.page,\r\n                sort: this.predicate + ',' + (this.reverse ? 'asc' : 'desc')\r\n            }\r\n        ]);\r\n        this.loadAll();\r\n    };\r\n    SalaryExtendedComponent.prototype.ngOnInit = function () {\r\n        var _this = this;\r\n        this.activatedRoute.data.subscribe(function (_a) {\r\n            var salary = _a.salary;\r\n            _this.salary = salary;\r\n            _this.loadAll();\r\n        });\r\n        this.accountService.identity().then(function (account) {\r\n            _this.currentAccount = account;\r\n        });\r\n        this.registerChangeInSalaries();\r\n    };\r\n    var _a, _b, _c, _d, _e, _f, _g;\r\n    SalaryExtendedComponent = tslib_1.__decorate([\r\n        core_1.Component({\r\n            selector: 'jhi-salary',\r\n            templateUrl: './salary-extended.component.html'\r\n        }),\r\n        tslib_1.__metadata(\"design:paramtypes\", [typeof (_a = typeof salary_extended_service_1.SalaryExtendedService !== \"undefined\" && salary_extended_service_1.SalaryExtendedService) === \"function\" ? _a : Object, typeof (_b = typeof ng_jhipster_1.JhiParseLinks !== \"undefined\" && ng_jhipster_1.JhiParseLinks) === \"function\" ? _b : Object, typeof (_c = typeof ng_jhipster_1.JhiAlertService !== \"undefined\" && ng_jhipster_1.JhiAlertService) === \"function\" ? _c : Object, typeof (_d = typeof core_2.AccountService !== \"undefined\" && core_2.AccountService) === \"function\" ? _d : Object, typeof (_e = typeof router_1.ActivatedRoute !== \"undefined\" && router_1.ActivatedRoute) === \"function\" ? _e : Object, typeof (_f = typeof router_1.Router !== \"undefined\" && router_1.Router) === \"function\" ? _f : Object, typeof (_g = typeof ng_jhipster_1.JhiEventManager !== \"undefined\" && ng_jhipster_1.JhiEventManager) === \"function\" ? _g : Object])\r\n    ], SalaryExtendedComponent);\r\n    return SalaryExtendedComponent;\r\n}(salary_1.SalaryComponent));\r\nexports.SalaryExtendedComponent = SalaryExtendedComponent;\r\n",{"version":3,"file":"C:\\Users\\hp\\Documents\\soptorshi-jhipster\\src\\main\\webapp\\app\\entities\\salary-extended\\salary-extended.component.ts","sourceRoot":"","sources":["C:\\Users\\hp\\Documents\\soptorshi-jhipster\\node_modules\\angular-router-loader\\src\\index.js!C:\\Users\\hp\\Documents\\soptorshi-jhipster\\node_modules\\tslint-loader\\index.js!C:\\Users\\hp\\Documents\\soptorshi-jhipster\\src\\main\\webapp\\app\\entities\\salary-extended\\salary-extended.component.ts"],"names":[],"mappings":";;;AAAA,sCAA6D;AAE7D,0CAAyD;AAGzD,2CAA8E;AAG9E,iCAA0C;AAG1C,qEAAkE;AAClE,8CAAsD;AAMtD;IAA6C,mDAAe;IAGxD,iCACc,aAAoC,EACpC,UAAyB,EACzB,eAAgC,EAChC,cAA8B,EAC9B,cAA8B,EAC9B,MAAc,EACd,YAA6B;QAP3C,YASI,kBAAM,aAAa,EAAE,UAAU,EAAE,eAAe,EAAE,cAAc,EAAE,cAAc,EAAE,MAAM,EAAE,YAAY,CAAC,SAC1G;QATa,mBAAa,GAAb,aAAa,CAAuB;QACpC,gBAAU,GAAV,UAAU,CAAe;QACzB,qBAAe,GAAf,eAAe,CAAiB;QAChC,oBAAc,GAAd,cAAc,CAAgB;QAC9B,oBAAc,GAAd,cAAc,CAAgB;QAC9B,YAAM,GAAN,MAAM,CAAQ;QACd,kBAAY,GAAZ,YAAY,CAAiB;;IAG3C,CAAC;IAED,yCAAO,GAAP;QAAA,iBA2BC;QA1BG,IAAI,IAAI,CAAC,aAAa,EAAE;YACpB,IAAI,CAAC,aAAa,GAAG,IAAI,CAAC,aAAa,GAAG,GAAG,GAAG,IAAI,CAAC,MAAM,CAAC,UAAU,CAAC;YACvE,IAAI,CAAC,aAAa;iBACb,MAAM,CAAC;gBACJ,IAAI,EAAE,IAAI,CAAC,IAAI,GAAG,CAAC;gBACnB,KAAK,EAAE,IAAI,CAAC,aAAa;gBACzB,IAAI,EAAE,IAAI,CAAC,YAAY;gBACvB,IAAI,EAAE,IAAI,CAAC,IAAI,EAAE;aACpB,CAAC;iBACD,SAAS,CACN,UAAC,GAA4B,IAAK,OAAA,KAAI,CAAC,gBAAgB,CAAC,GAAG,CAAC,IAAI,EAAE,GAAG,CAAC,OAAO,CAAC,EAA5C,CAA4C,EAC9E,UAAC,GAAsB,IAAK,OAAA,KAAI,CAAC,OAAO,CAAC,GAAG,CAAC,OAAO,CAAC,EAAzB,CAAyB,CACxD,CAAC;YACN,OAAO;SACV;QACD,IAAI,CAAC,aAAa;aACb,KAAK,CAAC;YACH,mBAAmB,EAAE,IAAI,CAAC,MAAM,CAAC,UAAU;YAC3C,IAAI,EAAE,IAAI,CAAC,IAAI,GAAG,CAAC;YACnB,IAAI,EAAE,IAAI,CAAC,YAAY;YACvB,IAAI,EAAE,IAAI,CAAC,IAAI,EAAE;SACpB,CAAC;aACD,SAAS,CACN,UAAC,GAA4B,IAAK,OAAA,KAAI,CAAC,gBAAgB,CAAC,GAAG,CAAC,IAAI,EAAE,GAAG,CAAC,OAAO,CAAC,EAA5C,CAA4C,EAC9E,UAAC,GAAsB,IAAK,OAAA,KAAI,CAAC,OAAO,CAAC,GAAG,CAAC,OAAO,CAAC,EAAzB,CAAyB,CACxD,CAAC;IACV,CAAC;IAED,0CAAQ,GAAR,UAAS,IAAY;QACjB,IAAI,IAAI,KAAK,IAAI,CAAC,YAAY,EAAE;YAC5B,IAAI,CAAC,YAAY,GAAG,IAAI,CAAC;YACzB,IAAI,CAAC,UAAU,EAAE,CAAC;SACrB;IACL,CAAC;IAED,4CAAU,GAAV;QACI,IAAI,CAAC,MAAM,CAAC,QAAQ,CAAC,CAAC,SAAS,CAAC,EAAE;YAC9B,WAAW,EAAE;gBACT,IAAI,EAAE,IAAI,CAAC,IAAI;gBACf,IAAI,EAAE,IAAI,CAAC,YAAY;gBACvB,MAAM,EAAE,IAAI,CAAC,aAAa;gBAC1B,IAAI,EAAE,IAAI,CAAC,SAAS,GAAG,GAAG,GAAG,CAAC,IAAI,CAAC,OAAO,CAAC,CAAC,CAAC,KAAK,CAAC,CAAC,CAAC,MAAM,CAAC;aAC/D;SACJ,CAAC,CAAC;QACH,IAAI,CAAC,OAAO,EAAE,CAAC;IACnB,CAAC;IAED,uCAAK,GAAL;QACI,IAAI,CAAC,IAAI,GAAG,CAAC,CAAC;QACd,IAAI,CAAC,aAAa,GAAG,EAAE,CAAC;QACxB,IAAI,CAAC,MAAM,CAAC,QAAQ,CAAC;YACjB,SAAS;YACT;gBACI,IAAI,EAAE,IAAI,CAAC,IAAI;gBACf,IAAI,EAAE,IAAI,CAAC,SAAS,GAAG,GAAG,GAAG,CAAC,IAAI,CAAC,OAAO,CAAC,CAAC,CAAC,KAAK,CAAC,CAAC,CAAC,MAAM,CAAC;aAC/D;SACJ,CAAC,CAAC;QACH,IAAI,CAAC,OAAO,EAAE,CAAC;IACnB,CAAC;IAED,sCAAI,GAAJ;QACI,MAAM,CAAC,OAAO,CAAC,IAAI,EAAE,CAAC;IAC1B,CAAC;IAED,wCAAM,GAAN,UAAO,KAAK;QACR,IAAI,CAAC,KAAK,EAAE;YACR,OAAO,IAAI,CAAC,KAAK,EAAE,CAAC;SACvB;QACD,IAAI,CAAC,IAAI,GAAG,CAAC,CAAC;QACd,IAAI,CAAC,aAAa,GAAG,KAAK,CAAC;QAC3B,IAAI,CAAC,MAAM,CAAC,QAAQ,CAAC;YACjB,SAAS;YACT;gBACI,MAAM,EAAE,IAAI,CAAC,aAAa;gBAC1B,IAAI,EAAE,IAAI,CAAC,IAAI;gBACf,IAAI,EAAE,IAAI,CAAC,SAAS,GAAG,GAAG,GAAG,CAAC,IAAI,CAAC,OAAO,CAAC,CAAC,CAAC,KAAK,CAAC,CAAC,CAAC,MAAM,CAAC;aAC/D;SACJ,CAAC,CAAC;QACH,IAAI,CAAC,OAAO,EAAE,CAAC;IACnB,CAAC;IAED,0CAAQ,GAAR;QAAA,iBASC;QARG,IAAI,CAAC,cAAc,CAAC,IAAI,CAAC,SAAS,CAAC,UAAC,EAAU;gBAAR,kBAAM;YACxC,KAAI,CAAC,MAAM,GAAG,MAAM,CAAC;YACrB,KAAI,CAAC,OAAO,EAAE,CAAC;QACnB,CAAC,CAAC,CAAC;QACH,IAAI,CAAC,cAAc,CAAC,QAAQ,EAAE,CAAC,IAAI,CAAC,UAAA,OAAO;YACvC,KAAI,CAAC,cAAc,GAAG,OAAO,CAAC;QAClC,CAAC,CAAC,CAAC;QACH,IAAI,CAAC,wBAAwB,EAAE,CAAC;IACpC,CAAC;;IA1GQ,uBAAuB;QAJnC,gBAAS,CAAC;YACP,QAAQ,EAAE,YAAY;YACtB,WAAW,EAAE,kCAAkC;SAClD,CAAC;qEAK+B,+CAAqB,oBAArB,+CAAqB,oDACxB,2BAAa,oBAAb,2BAAa,oDACR,6BAAe,oBAAf,6BAAe,oDAChB,qBAAc,oBAAd,qBAAc,oDACd,uBAAc,oBAAd,uBAAc,oDACtB,eAAM,oBAAN,eAAM,oDACA,6BAAe,oBAAf,6BAAe;OAVlC,uBAAuB,CA2GnC;IAAD,8BAAC;CAAA,AA3GD,CAA6C,wBAAe,GA2G3D;AA3GY,0DAAuB","sourcesContent":["import { Component, OnInit, OnDestroy } from '@angular/core';\r\nimport { HttpErrorResponse, HttpHeaders, HttpResponse } from '@angular/common/http';\r\nimport { ActivatedRoute, Router } from '@angular/router';\r\nimport { Subscription } from 'rxjs';\r\nimport { filter, map } from 'rxjs/operators';\r\nimport { JhiEventManager, JhiParseLinks, JhiAlertService } from 'ng-jhipster';\r\n\r\nimport { ISalary } from 'app/shared/model/salary.model';\r\nimport { AccountService } from 'app/core';\r\n\r\nimport { ITEMS_PER_PAGE } from 'app/shared';\r\nimport { SalaryExtendedService } from './salary-extended.service';\r\nimport { SalaryComponent } from 'app/entities/salary';\r\n\r\n@Component({\r\n    selector: 'jhi-salary',\r\n    templateUrl: './salary-extended.component.html'\r\n})\r\nexport class SalaryExtendedComponent extends SalaryComponent implements OnInit, OnDestroy {\r\n    salary: ISalary;\r\n\r\n    constructor(\r\n        protected salaryService: SalaryExtendedService,\r\n        protected parseLinks: JhiParseLinks,\r\n        protected jhiAlertService: JhiAlertService,\r\n        protected accountService: AccountService,\r\n        protected activatedRoute: ActivatedRoute,\r\n        protected router: Router,\r\n        protected eventManager: JhiEventManager\r\n    ) {\r\n        super(salaryService, parseLinks, jhiAlertService, accountService, activatedRoute, router, eventManager);\r\n    }\r\n\r\n    loadAll() {\r\n        if (this.currentSearch) {\r\n            this.currentSearch = this.currentSearch + ' ' + this.salary.employeeId;\r\n            this.salaryService\r\n                .search({\r\n                    page: this.page - 1,\r\n                    query: this.currentSearch,\r\n                    size: this.itemsPerPage,\r\n                    sort: this.sort()\r\n                })\r\n                .subscribe(\r\n                    (res: HttpResponse<ISalary[]>) => this.paginateSalaries(res.body, res.headers),\r\n                    (res: HttpErrorResponse) => this.onError(res.message)\r\n                );\r\n            return;\r\n        }\r\n        this.salaryService\r\n            .query({\r\n                'employeeId.equals': this.salary.employeeId,\r\n                page: this.page - 1,\r\n                size: this.itemsPerPage,\r\n                sort: this.sort()\r\n            })\r\n            .subscribe(\r\n                (res: HttpResponse<ISalary[]>) => this.paginateSalaries(res.body, res.headers),\r\n                (res: HttpErrorResponse) => this.onError(res.message)\r\n            );\r\n    }\r\n\r\n    loadPage(page: number) {\r\n        if (page !== this.previousPage) {\r\n            this.previousPage = page;\r\n            this.transition();\r\n        }\r\n    }\r\n\r\n    transition() {\r\n        this.router.navigate(['/salary'], {\r\n            queryParams: {\r\n                page: this.page,\r\n                size: this.itemsPerPage,\r\n                search: this.currentSearch,\r\n                sort: this.predicate + ',' + (this.reverse ? 'asc' : 'desc')\r\n            }\r\n        });\r\n        this.loadAll();\r\n    }\r\n\r\n    clear() {\r\n        this.page = 0;\r\n        this.currentSearch = '';\r\n        this.router.navigate([\r\n            '/salary',\r\n            {\r\n                page: this.page,\r\n                sort: this.predicate + ',' + (this.reverse ? 'asc' : 'desc')\r\n            }\r\n        ]);\r\n        this.loadAll();\r\n    }\r\n\r\n    back() {\r\n        window.history.back();\r\n    }\r\n\r\n    search(query) {\r\n        if (!query) {\r\n            return this.clear();\r\n        }\r\n        this.page = 0;\r\n        this.currentSearch = query;\r\n        this.router.navigate([\r\n            '/salary',\r\n            {\r\n                search: this.currentSearch,\r\n                page: this.page,\r\n                sort: this.predicate + ',' + (this.reverse ? 'asc' : 'desc')\r\n            }\r\n        ]);\r\n        this.loadAll();\r\n    }\r\n\r\n    ngOnInit() {\r\n        this.activatedRoute.data.subscribe(({ salary }) => {\r\n            this.salary = salary;\r\n            this.loadAll();\r\n        });\r\n        this.accountService.identity().then(account => {\r\n            this.currentAccount = account;\r\n        });\r\n        this.registerChangeInSalaries();\r\n    }\r\n}\r\n"]}]}